{"runInfo": {"sut": "PGBOUNCER", "workload": "W5_HTAP", "loadMode": "open-loop", "targetRps": 1, "concurrency": 0, "poolSize": 20, "instanceId": 2, "totalInstances": 4, "configuredDbConnectionBudget": 100, "configuredReplicas": 4, "seed": 42, "durationSeconds": 900, "timestamp": "2026-07-01T16:49:01Z", "openLoopAttemptedOps": 901, "openLoopMissedOpportunities": 0, "openLoopSchedulingDelayMs": 0.0, "clientPooling": "hikari"}, "attemptedRps": 0.8828373864485931, "achievedThroughputRps": 0.8828373864485931, "successfulThroughputRps": 0.8828373864485931, "errorThroughputRps": 0.0, "totalThroughputRps": 0.8828373864485931, "errorRate": 0.0, "totalRequests": 901, "successfulRequests": 901, "failedRequests": 0, "latencyMs": {"p50": 2.597, "p95": 960.511, "p99": 6303.743, "p999": 9764.863, "max": 9764.863, "mean": 199.30996340954496, "meanSuccessful": 199.31234295227523, "meanFailed": 0.0, "meanTotal": 199.30996340954496}, "errorsByType": {}, "firstErrorMessageByType": {}, "appCpuMedian": 0.1002004008016032, "gcPauseMsTotal": 3}