{"runInfo": {"sut": "OJP", "workload": "W5_HTAP", "loadMode": "open-loop", "targetRps": 4, "concurrency": 0, "poolSize": 48, "instanceId": 6, "totalInstances": 16, "configuredDbConnectionBudget": 48, "configuredReplicas": 16, "seed": 42, "durationSeconds": 900, "timestamp": "2026-07-15T22:04:43Z", "openLoopAttemptedOps": 3601, "openLoopMissedOpportunities": 0, "openLoopSchedulingDelayMs": 0.0, "clientPooling": "none", "ojpVirtualConnectionMode": "PER_WORKER", "ojpPoolSharing": "SHARED", "ojpPropertiesUsed": {"ojp.slowQueryThresholdMs": "1000", "ojp.connection.pool.minimumIdle": "48", "ojp.queueLimit": "200", "ojp.connection.pool.maxLifetime": "30000", "ojp.connection.pool.connectionTimeout": "30000", "ojp.connection.pool.idleTimeout": "30000"}, "clientVirtualConnectionsOpenedTotal": 4801, "clientVirtualConnectionsMaxConcurrent": 86}, "attemptedRps": 3.8567941590078796, "achievedThroughputRps": 3.2762936218842276, "successfulThroughputRps": 3.2762936218842276, "errorThroughputRps": 0.5869267423316629, "totalThroughputRps": 3.8632203642158904, "errorRate": 0.15192680898253397, "totalRequests": 3607, "successfulRequests": 3059, "failedRequests": 548, "latencyMs": {"p50": 4.033, "p95": 25.903, "p99": 34308.095, "p999": 39780.351, "max": 48693.247, "mean": 1364.859433577488, "meanSuccessful": 589.2761284733573, "meanFailed": 5694.239204198905, "meanTotal": 1364.859433577488}, "errorsByType": {"SQLTransientConnectionException": 548}, "firstErrorMessageByType": {"SQLTransientConnectionException": "Timeout waiting for slow operation slot for operation: e9cb50da3e8545"}, "appCpuMedian": 0.0751079679978097, "gcPauseMsTotal": 98}