{"runInfo": {"sut": "HIKARI_DISCIPLINED", "workload": "W5_HTAP", "loadMode": "open-loop", "targetRps": 1, "concurrency": 0, "poolSize": 20, "instanceId": 2, "totalInstances": 4, "configuredDbConnectionBudget": 80, "configuredReplicas": 4, "seed": 42, "durationSeconds": 900, "timestamp": "2026-07-11T13:13:04Z", "openLoopAttemptedOps": 901, "openLoopMissedOpportunities": 0, "openLoopSchedulingDelayMs": 0.0, "clientPooling": "hikari"}, "attemptedRps": 0.99980248075297, "achievedThroughputRps": 1.0009121394441498, "successfulThroughputRps": 1.0009121394441498, "errorThroughputRps": 0.0, "totalThroughputRps": 1.0009121394441498, "errorRate": 0.0, "totalRequests": 902, "successfulRequests": 902, "failedRequests": 0, "latencyMs": {"p50": 2.529, "p95": 578.047, "p99": 9453.567, "p999": 15097.855, "max": 15097.855, "mean": 292.07423145232815, "meanSuccessful": 292.09108314855877, "meanFailed": 0.0, "meanTotal": 292.07423145232815}, "errorsByType": {}, "firstErrorMessageByType": {}, "appCpuMedian": 0.10015022533800699, "gcPauseMsTotal": 11}