{"runInfo": {"sut": "HIKARI_DISCIPLINED", "workload": "W5_HTAP", "loadMode": "open-loop", "targetRps": 1, "concurrency": 0, "poolSize": 20, "instanceId": 2, "totalInstances": 4, "configuredDbConnectionBudget": 80, "configuredReplicas": 4, "seed": 42, "durationSeconds": 900, "timestamp": "2026-07-11T11:40:09Z", "openLoopAttemptedOps": 900, "openLoopMissedOpportunities": 0, "openLoopSchedulingDelayMs": 0.0, "clientPooling": "hikari"}, "attemptedRps": 0.9998823667803788, "achievedThroughputRps": 0.9998823667803788, "successfulThroughputRps": 0.9998823667803788, "errorThroughputRps": 0.0, "totalThroughputRps": 0.9998823667803788, "errorRate": 0.0, "totalRequests": 901, "successfulRequests": 901, "failedRequests": 0, "latencyMs": {"p50": 2.391, "p95": 526.847, "p99": 10280.959, "p999": 14827.519, "max": 14827.519, "mean": 296.14635564483905, "meanSuccessful": 296.1575937846837, "meanFailed": 0.0, "meanTotal": 296.14635564483905}, "errorsByType": {}, "firstErrorMessageByType": {}, "appCpuMedian": 0.10010010010010009, "gcPauseMsTotal": 11}