{"runInfo": {"sut": "PGBOUNCER", "workload": "W5_HTAP", "loadMode": "open-loop", "targetRps": 1, "concurrency": 0, "poolSize": 20, "instanceId": 0, "totalInstances": 16, "configuredDbConnectionBudget": 100, "configuredReplicas": 16, "seed": 42, "durationSeconds": 900, "timestamp": "2026-07-14T22:19:57Z", "openLoopAttemptedOps": 901, "openLoopMissedOpportunities": 0, "openLoopSchedulingDelayMs": 0.0, "clientPooling": "hikari"}, "attemptedRps": 0.9636291493004866, "achievedThroughputRps": 0.964698660010032, "successfulThroughputRps": 0.964698660010032, "errorThroughputRps": 0.0, "totalThroughputRps": 0.964698660010032, "errorRate": 0.0, "totalRequests": 902, "successfulRequests": 902, "failedRequests": 0, "latencyMs": {"p50": 3.563, "p95": 8863.743, "p99": 22380.543, "p999": 41844.735, "max": 41844.735, "mean": 1361.3243301696232, "meanSuccessful": 1361.383253880266, "meanFailed": 0.0, "meanTotal": 1361.3243301696232}, "errorsByType": {}, "firstErrorMessageByType": {}, "appCpuMedian": 0.025015634771732333, "gcPauseMsTotal": 2}