{"runInfo": {"sut": "OJP", "workload": "W5_HTAP", "loadMode": "open-loop", "targetRps": 8, "concurrency": 0, "poolSize": 12, "instanceId": 2, "totalInstances": 4, "configuredDbConnectionBudget": 12, "configuredReplicas": 4, "seed": 42, "durationSeconds": 900, "timestamp": "2026-07-12T05:55:17Z", "openLoopAttemptedOps": 7201, "openLoopMissedOpportunities": 0, "openLoopSchedulingDelayMs": 0.0, "clientPooling": "none", "ojpVirtualConnectionMode": "PER_WORKER", "ojpPoolSharing": "SHARED", "ojpPropertiesUsed": {"ojp.slowQueryThresholdMs": "1000", "ojp.connection.pool.minimumIdle": "12", "ojp.queueLimit": "200", "ojp.connection.pool.maxLifetime": "30000", "ojp.connection.pool.connectionTimeout": "30000", "ojp.connection.pool.idleTimeout": "30000"}, "clientVirtualConnectionsOpenedTotal": 9601, "clientVirtualConnectionsMaxConcurrent": 264}, "attemptedRps": 7.968925506426821, "achievedThroughputRps": 3.864392149485135, "successfulThroughputRps": 3.864392149485135, "errorThroughputRps": 4.203024451244142, "totalThroughputRps": 8.067416600729278, "errorRate": 0.5209876543209877, "totalRequests": 7290, "successfulRequests": 3492, "failedRequests": 3798, "latencyMs": {"p50": 5.099, "p95": 4444.159, "p99": 32522.239, "p999": 189267.967, "max": 275775.487, "mean": 10020.873503469822, "meanSuccessful": 1329.934321019473, "meanFailed": 18011.538056373352, "meanTotal": 10020.873503469822}, "errorsByType": {"SQLTransientConnectionException": 3798}, "firstErrorMessageByType": {"SQLTransientConnectionException": "Timeout waiting for fast operation slot for operation: e7282124a6fbdd3c"}, "appCpuMedian": 0.35070140280561124, "gcPauseMsTotal": 261}