{"runInfo": {"sut": "HIKARI_DISCIPLINED", "workload": "W5_HTAP", "loadMode": "open-loop", "targetRps": 4, "concurrency": 0, "poolSize": 20, "instanceId": 1, "totalInstances": 4, "configuredDbConnectionBudget": 80, "configuredReplicas": 4, "seed": 42, "durationSeconds": 900, "timestamp": "2026-07-05T02:23:52Z", "openLoopAttemptedOps": 3600, "openLoopMissedOpportunities": 0, "openLoopSchedulingDelayMs": 0.0, "clientPooling": "hikari"}, "attemptedRps": 3.8721679193952494, "achievedThroughputRps": 3.87754443691732, "successfulThroughputRps": 3.87754443691732, "errorThroughputRps": 0.0, "totalThroughputRps": 3.87754443691732, "errorRate": 0.0, "totalRequests": 3606, "successfulRequests": 3606, "failedRequests": 0, "latencyMs": {"p50": 6.063, "p95": 10133.503, "p99": 28704.767, "p999": 68878.335, "max": 76677.119, "mean": 1263.6828225024958, "meanSuccessful": 1263.7189057127011, "meanFailed": 0.0, "meanTotal": 1263.6828225024958}, "errorsByType": {}, "firstErrorMessageByType": {}, "appCpuMedian": 0.20020020020020018, "gcPauseMsTotal": 16}