{"runInfo": {"sut": "OJP", "workload": "W5_HTAP", "loadMode": "open-loop", "targetRps": 2, "concurrency": 0, "poolSize": 48, "instanceId": 5, "totalInstances": 16, "configuredDbConnectionBudget": 48, "configuredReplicas": 16, "seed": 42, "durationSeconds": 900, "timestamp": "2026-07-15T02:11:41Z", "openLoopAttemptedOps": 1801, "openLoopMissedOpportunities": 0, "openLoopSchedulingDelayMs": 0.0, "clientPooling": "none", "ojpVirtualConnectionMode": "PER_WORKER", "ojpPoolSharing": "SHARED", "ojpPropertiesUsed": {"ojp.slowQueryThresholdMs": "1000", "ojp.connection.pool.minimumIdle": "48", "ojp.queueLimit": "200", "ojp.connection.pool.maxLifetime": "30000", "ojp.connection.pool.connectionTimeout": "30000", "ojp.connection.pool.idleTimeout": "30000"}, "clientVirtualConnectionsOpenedTotal": 2401, "clientVirtualConnectionsMaxConcurrent": 20}, "attemptedRps": 1.9696212443500523, "achievedThroughputRps": 1.7158999069323888, "successfulThroughputRps": 1.7158999069323888, "errorThroughputRps": 0.25590859032643654, "totalThroughputRps": 1.9718084972588252, "errorRate": 0.129783693843594, "totalRequests": 1803, "successfulRequests": 1569, "failedRequests": 234, "latencyMs": {"p50": 5.899, "p95": 51.231, "p99": 35258.367, "p999": 49020.927, "max": 53477.375, "mean": 1560.672234057127, "meanSuccessful": 1200.5783358827277, "meanFailed": 3975.1820011282052, "meanTotal": 1560.672234057127}, "errorsByType": {"SQLTransientConnectionException": 234}, "firstErrorMessageByType": {"SQLTransientConnectionException": "Timeout waiting for slow operation slot for operation: ac3451c82f425cef"}, "appCpuMedian": 0.06252735596258802, "gcPauseMsTotal": 58}